Metadata-Version: 2.1
Name: nbclient
Version: 0.7.0
Summary: A client library for executing notebooks. Formerly nbconvert's ExecutePreprocessor.
Home-page: https://jupyter.org
Author: Jupyter Development Team
Author-email: jupyter@googlegroups.com
License: BSD
Project-URL: Documentation, https://nbclient.readthedocs.io
Project-URL: Funding, https://numfocus.org/
Project-URL: Source, https://github.com/jupyter/nbclient
Project-URL: Tracker, https://github.com/jupyter/nbclient/issues
Keywords: jupyter,pipeline,notebook,executor
Platform: Linux
Platform: Mac OS X
Platform: Windows
Classifier: Intended Audience :: Developers
Classifier: Intended Audience :: System Administrators
Classifier: Intended Audience :: Science/Research
Classifier: License :: OSI Approved :: BSD License
Classifier: Programming Language :: Python
Classifier: Programming Language :: Python :: 3
Classifier: Programming Language :: Python :: 3.7
Classifier: Programming Language :: Python :: 3.8
Classifier: Programming Language :: Python :: 3.9
Classifier: Programming Language :: Python :: 3.10
Requires-Python: >=3.7.0
Provides-Extra: test
Provides-Extra: sphinx
License-File: LICENSE
